Workbook

Sheet Personal
A1: CAD | F1: ETF | K1: USD | P1: USDStock | U1: Oranges | AB1: CAD | AL1: ETF | AV1: USD | BF1: USDStock | BP1: Oranges
Z2: Personal
A3: Transaction | B3: Account | C3: DR | D3: CR | F3: Transaction | G3: Account | H3: DR | I3: CR | K3: Transaction | L3: Account | M3: DR | N3: CR | P3: Transaction | Q3: Account | R3: DR | S3: CR | U3: Transaction | V3: Account | W3: DR | X3: CR | AB3: Net Assets | AL3: Net Assets | AV3: Net Assets | BF3: Net Assets | BP3: Net Assets
A4: IS | B4: Cash | C4: 30000 | F4: T1 | G4: Investment Portfolio | H4: =C6/265 -> 37.735849 | K4: IS | L4: Accounts Receivable - Roddy | M4: 300 | P4: T9 | Q4: Investment Portfolio | R4: =N11/100 -> 50 | U4: T10 | V4: Inventory | W4: ='Personal (Basis)'!$AN$5 -> 1304.3478 | AC4: Assets | AM4: Assets | AW4: Assets | BG4: Assets | BQ4: Assets
A5: IS | B5: Initial State | D5: =C4 -> 30000 | F5: T1 | G5: Net Transfers - CAD | I5: =H4 -> 37.735849 | K5: IS | L5: Initial State | N5: =M4 -> 300 | P5: T9 | Q5: Net Transfers | S5: =R4 -> 50 | U5: T10 | V5: Net Transfers | X5: =W4 -> 1304.3478 | AA5: 1 | AD5: Cash | AG5: {=SUMPRODUCT(--(INDIRECT(_xlfn.CONCAT($Z$2,"_",AB$1,"[Account]"))=AD5),INDIRECT(_xlfn.CONCAT($Z$2,"_",AB$1,"[DR]"))-INDIRECT(_xlfn.CONCAT($Z$2,"_",AB$1,"[CR]")))*AA5} -> 21846.501 | AK5: 1 | AN5: Investment Portfolio | AQ5: {=SUMPRODUCT(--(INDIRECT(_xlfn.CONCAT($Z$2,"_",AL$1,"[Account]"))=AN5),INDIRECT(_xlfn.CONCAT($Z$2,"_",AL$1,"[DR]"))-INDIRECT(_xlfn.CONCAT($Z$2,"_",AL$1,"[CR]")))*AK5} -> 28.672257 | AU5: 1 | AX5: Cash | BA5: {=SUMPRODUCT(--(INDIRECT(_xlfn.CONCAT($Z$2,"_",AV$1,"[Account]"))=AX5),INDIRECT(_xlfn.CONCAT($Z$2,"_",AV$1,"[DR]"))-INDIRECT(_xlfn.CONCAT($Z$2,"_",AV$1,"[CR]")))*AU5} -> 2608.6957 | BE5: 1 | BH5: Investment Portfolio | BK5: {=SUMPRODUCT(--(INDIRECT(_xlfn.CONCAT($Z$2,"_",BF$1,"[Account]"))=BH5),INDIRECT(_xlfn.CONCAT($Z$2,"_",BF$1,"[DR]"))-INDIRECT(_xlfn.CONCAT($Z$2,"_",BF$1,"[CR]")))*BE5} -> 0 | BO5: 1 | BR5: Inventory | BU5: {=SUMPRODUCT(--(INDIRECT(_xlfn.CONCAT($Z$2,"_",BP$1,"[Account]"))=BR5),INDIRECT(_xlfn.CONCAT($Z$2,"_",BP$1,"[DR]"))-INDIRECT(_xlfn.CONCAT($Z$2,"_",BP$1,"[CR]")))*BO5} -> 0
A6: T1 | B6: Net Transfers - ETF | C6: =D7 -> 10000 | F6: T5 | G6: Investment Portfolio | H6: =C16/270 -> 0.37037037 | L6: Cash | M6: 300 | P6: T16 | Q6: Net Transfers | R6: =R4 -> 50 | U6: T11 | V6: Net Transfers | W6: 300 | AD6: Total Assets | AH6: =SUM(AG5:AG6) -> 21846.501 | AN6: Total Assets | AR6: =SUM(AQ5:AQ6) -> 28.672257 | AU6: 1 | AX6: Accounts Receivable - Roddy | BA6: {=SUMPRODUCT(--(INDIRECT(_xlfn.CONCAT($Z$2,"_",AV$1,"[Account]"))=AX6),INDIRECT(_xlfn.CONCAT($Z$2,"_",AV$1,"[DR]"))-INDIRECT(_xlfn.CONCAT($Z$2,"_",AV$1,"[CR]")))*AU6} -> 0 | BH6: Total Assets | BL6: =SUM(BK5:BK6) -> 0 | BR6: Total Assets | BV6: =SUM(BU5:BU6) -> 0
A7: T1 | B7: Cash | D7: 10000 | F7: T5 | G7: Net Transfers - CAD | I7: =H6 -> 0.37037037 | L7: Accounts Receivable - Roddy | N7: =M6 -> 300 | P7: T16 | Q7: Investment Portfolio | S7: =R6 -> 50 | U7: T11 | V7: Inventory | X7: =W6 -> 300 | AC7: Liabilities | AM7: Net Assets | AS7: =SUM(AR6:AR7) -> 28.672257 | AX7: Total Assets | BB7: =SUM(BA5:BA7) -> 2608.6957 | BG7: Net Assets | BM7: =SUM(BL6:BL7) -> 0 | BQ7: Net Assets | BW7: =SUM(BV6:BV7) -> 0
A8: T2 | B8: Grocery Expense | C8: 120 | F8: T6 | G8: Net Transfers - CAD | H8: =-'Personal (Basis)'!$L$6 -> 9.4339623 | K8: T8 | L8: Cash | M8: ='Personal (Basis)'!$V$12 -> 9000 | U8: T12 | V8: Net Transfers | W8: 700 | AA8: -1 | AD8: Tax Payable | AG8: {=SUMPRODUCT(--(INDIRECT(_xlfn.CONCAT($Z$2,"_",AB$1,"[Account]"))=AD8),INDIRECT(_xlfn.CONCAT($Z$2,"_",AB$1,"[DR]"))-INDIRECT(_xlfn.CONCAT($Z$2,"_",AB$1,"[CR]")))*AA8} -> 800 | AW8: Net Assets | BC8: =SUM(BB7:BB8) -> 2608.6957
A9: T2 | B9: Cash | D9: =C8 -> 120 | F9: T6 | G9: Investment Portfolio | I9: =H8 -> 9.4339623 | K9: T8 | L9: Net Transfers - CAD | N9: =M8 -> 9000 | U9: T12 | V9: Inventory | X9: =W8 -> 700 | AD9: Less: Total Liabilities | AH9: =-SUM(AG8:AG9) -> -800 | AL9: Net Worth | BF9: Net Worth | BP9: Net Worth
A10: T3 | B10: Telecom Expense | C10: 110 | K10: T9 | L10: Net Transfers - USDStock | M10: 5000 | U10: T13 | V10: Inventory | W10: ='Personal (Basis)'!$AN$14+'Personal (Basis)'!$AN$22 -> 1000 | AC10: Net Assets | AI10: =SUM(AH6:AH9) -> 21046.501 | AK10: -1 | AM10: Net Transfers - CAD | AR10: {=SUMPRODUCT(--(INDIRECT(_xlfn.CONCAT($Z$2,"_",AL$1,"[Account]"))=AM10),INDIRECT(_xlfn.CONCAT($Z$2,"_",AL$1,"[DR]"))-INDIRECT(_xlfn.CONCAT($Z$2,"_",AL$1,"[CR]")))*AK10} -> 28.672257 | AV10: Net Worth | BE10: -1 | BG10: Net Transfers | BL10: {=SUMPRODUCT(--(INDIRECT(_xlfn.CONCAT($Z$2,"_",BF$1,"[Account]"))=BG10),INDIRECT(_xlfn.CONCAT($Z$2,"_",BF$1,"[DR]"))-INDIRECT(_xlfn.CONCAT($Z$2,"_",BF$1,"[CR]")))*BE10} -> 0 | BO10: -1 | BQ10: Net Transfers | BV10: {=SUMPRODUCT(--(INDIRECT(_xlfn.CONCAT($Z$2,"_",BP$1,"[Account]"))=BQ10),INDIRECT(_xlfn.CONCAT($Z$2,"_",BP$1,"[DR]"))-INDIRECT(_xlfn.CONCAT($Z$2,"_",BP$1,"[CR]")))*BO10} -> 0
A11: T3 | B11: GST Expense | C11: =D12-C10 -> 5 | K11: T9 | L11: Cash | N11: =M10 -> 5000 | U11: T13 | V11: Net Transfers | X11: =W10 -> 1000 | AM11: Net Worth | AS11: =SUM(AR10:AR11) -> 28.672257 | AU11: -1 | AW11: Initial State | BB11: {=SUMPRODUCT(--(INDIRECT(_xlfn.CONCAT($Z$2,"_",AV$1,"[Account]"))=AW11),INDIRECT(_xlfn.CONCAT($Z$2,"_",AV$1,"[DR]"))-INDIRECT(_xlfn.CONCAT($Z$2,"_",AV$1,"[CR]")))*AU11} -> 300 | BG11: Net Worth | BM11: =SUM(BL10:BL11) -> 0 | BQ11: Net Worth | BW11: =SUM(BV10:BV11) -> 0
A12: T3 | B12: Cash | D12: 115 | K12: T10 | L12: Net Transfers - Oranges | M12: 3000 | U12: T14 | V12: Net Transfers | W12: =(W4-X7-X9+W10)*40% -> 521.73913 | AB12: Net Worth | AL12: Ledger Balance | AS12: =AS7-AS11 -> 0 | AU12: -1 | AW12: Net Transfers | BB12: {=SUMPRODUCT(--(INDIRECT(_xlfn.CONCAT($Z$2,"_",AV$1,"[Account]"))=AW12),INDIRECT(_xlfn.CONCAT($Z$2,"_",AV$1,"[DR]"))-INDIRECT(_xlfn.CONCAT($Z$2,"_",AV$1,"[CR]")))*AU12} -> 0 | BF12: Ledger Balance | BM12: =BM7-BM11 -> 0 | BP12: Ledger Balance | BW12: =BW7-BW11 -> 0
A13: T4 | B13: Cash | C13: 3000 | K13: T10 | L13: Cash | N13: =M12 -> 3000 | U13: T14 | V13: Inventory | X13: =W12 -> 521.73913 | AA13: -1 | AC13: Initial State | AH13: {=SUMPRODUCT(--(INDIRECT(_xlfn.CONCAT($Z$2,"_",AB$1,"[Account]"))=AC13),INDIRECT(_xlfn.CONCAT($Z$2,"_",AB$1,"[DR]"))-INDIRECT(_xlfn.CONCAT($Z$2,"_",AB$1,"[CR]")))*AA13} -> 30000 | AW13: Net Income
A14: T4 | B14: Tax Payable | D14: 800 | K14: T11 | L14: Cash | M14: =W6*4 -> 1200 | U14: T15 | V14: Net Transfers | W14: =W4-X7-X9+W10-X13 -> 782.6087 | AC14: Net Transfers | AU14: -1 | AX14: Capital Gains | BA14: {=SUMPRODUCT(--(INDIRECT(_xlfn.CONCAT($Z$2,"_",AV$1,"[Account]"))=AX14),INDIRECT(_xlfn.CONCAT($Z$2,"_",AV$1,"[DR]"))-INDIRECT(_xlfn.CONCAT($Z$2,"_",AV$1,"[CR]")))*AU14} -> 0
A15: T4 | B15: Employment Income | D15: =C13-D14 -> 2200 | K15: T11 | L15: Net Transfers - Oranges | N15: ='Personal (Basis)'!$Y$21 -> 690 | U15: =U14 -> T15 | V15: Inventory | X15: =W14 -> 782.6087 | AA15: -1 | AD15: Net Transfers - ETF | AF15: {=SUMPRODUCT(--(INDIRECT(_xlfn.CONCAT($Z$2,"_",AB$1,"[Account]"))=AD15),INDIRECT(_xlfn.CONCAT($Z$2,"_",AB$1,"[DR]"))-INDIRECT(_xlfn.CONCAT($Z$2,"_",AB$1,"[CR]")))*AA15} -> -7600 | AU15: -1 | AX15: Profit | BA15: {=SUMPRODUCT(--(INDIRECT(_xlfn.CONCAT($Z$2,"_",AV$1,"[Account]"))=AX15),INDIRECT(_xlfn.CONCAT($Z$2,"_",AV$1,"[DR]"))-INDIRECT(_xlfn.CONCAT($Z$2,"_",AV$1,"[CR]")))*AU15} -> 1818.6957
A16: T5 | B16: Net Transfers - ETF | C16: 100 | K16: T11 | L16: Profit | N16: =M14-N15 -> 510 | AA16: -1 | AD16: Net Transfers - USD | AF16: {=SUMPRODUCT(--(INDIRECT(_xlfn.CONCAT($Z$2,"_",AB$1,"[Account]"))=AD16),INDIRECT(_xlfn.CONCAT($Z$2,"_",AB$1,"[DR]"))-INDIRECT(_xlfn.CONCAT($Z$2,"_",AB$1,"[CR]")))*AA16} -> -12000 | AX16: Net Income | BB16: =SUM(BA14:BA16) -> 1818.6957
A17: T5 | B17: Dividend Income | D17: =C16 -> 100 | K17: T13 | L17: Net Transfers - Oranges | M17: =M6+M8-N11-N13+M14 -> 2500 | AA17: -1 | AD17: Net Transfers - Oranges | AF17: {=SUMPRODUCT(--(INDIRECT(_xlfn.CONCAT($Z$2,"_",AB$1,"[Account]"))=AD17),INDIRECT(_xlfn.CONCAT($Z$2,"_",AB$1,"[DR]"))-INDIRECT(_xlfn.CONCAT($Z$2,"_",AB$1,"[CR]")))*AA17} -> 4755.3623 | AU17: -1 | AW17: Net Worth | BC17: =SUM(BB11:BB17) -> 2118.6957
A18: T6 | B18: Cash | C18: ='Personal (Basis)'!$C$20 -> 2735.8491 | K18: T13 | L18: Cash | N18: =M17 -> 2500 | AD18: Net Transfers | AG18: =SUM(AF15:AF17) -> -14844.638 | AV18: Ledger Balance | BC18: =BC8-BC17 -> 490
A19: T6 | B19: Net Transfers - ETF | D19: ='Personal (Basis)'!$D$20 -> 2500 | K19: T14 | L19: Cash | M19: ='Personal (Basis)'!$V$32+'Personal (Basis)'!$V$28 -> 2608.6957 | AC19: Net Income
A20: T6 | B20: Capital Gains | D20: ='Personal (Basis)'!$I$20 -> 235.84906 | K20: T14 | L20: Net Transfers - Oranges | N20: ='Personal (Basis)'!$Y$28+'Personal (Basis)'!$Y$32 -> 1300 | AD20: Income
A21: T7 | B21: Transportation Expense | C21: 200 | K21: T14 | L21: Profit | N21: ='Personal (Basis)'!$AB$28+'Personal (Basis)'!$AB$32 -> 1308.6957 | AA21: -1 | AE21: Employment Income | AF21: {=SUMPRODUCT(--(INDIRECT(_xlfn.CONCAT($Z$2,"_",AB$1,"[Account]"))=AE21),INDIRECT(_xlfn.CONCAT($Z$2,"_",AB$1,"[DR]"))-INDIRECT(_xlfn.CONCAT($Z$2,"_",AB$1,"[CR]")))*AA21} -> 2200
A22: T7 | B22: Cash | D22: =C21 -> 200 | K22: T16 | L22: Cash | AA22: -1 | AE22: Profit | AF22: {=SUMPRODUCT(--(INDIRECT(_xlfn.CONCAT($Z$2,"_",AB$1,"[Account]"))=AE22),INDIRECT(_xlfn.CONCAT($Z$2,"_",AB$1,"[DR]"))-INDIRECT(_xlfn.CONCAT($Z$2,"_",AB$1,"[CR]")))*AA22} -> 3790.2899
A23: T8 | B23: Net Transfers - USD | C23: 12000 | AA23: -1 | AE23: Capital Gains | AF23: {=SUMPRODUCT(--(INDIRECT(_xlfn.CONCAT($Z$2,"_",AB$1,"[Account]"))=AE23),INDIRECT(_xlfn.CONCAT($Z$2,"_",AB$1,"[DR]"))-INDIRECT(_xlfn.CONCAT($Z$2,"_",AB$1,"[CR]")))*AA23} -> 235.84906
A24: T8 | B24: Cash | D24: =C23 -> 12000 | AA24: -1 | AE24: Dividend Income | AF24: {=SUMPRODUCT(--(INDIRECT(_xlfn.CONCAT($Z$2,"_",AB$1,"[Account]"))=AE24),INDIRECT(_xlfn.CONCAT($Z$2,"_",AB$1,"[DR]"))-INDIRECT(_xlfn.CONCAT($Z$2,"_",AB$1,"[CR]")))*AA24} -> 100
A25: T12 | B25: Cash | C25: =W8*5.5 -> 3850 | AE25: Total Income | AG25: =SUM(AF21:AF25) -> 6326.1389
A26: T12 | B26: Net Transfers - Oranges | D26: ='Personal (Basis)'!$D$24 -> 2146.6667 | AD26: Expenses
A27: T12 | B27: Profit | D27: =C25-D26 -> 1703.3333 | AA27: 1 | AE27: Grocery Expense | AF27: {=SUMPRODUCT(--(INDIRECT(_xlfn.CONCAT($Z$2,"_",AB$1,"[Account]"))=AE27),INDIRECT(_xlfn.CONCAT($Z$2,"_",AB$1,"[DR]"))-INDIRECT(_xlfn.CONCAT($Z$2,"_",AB$1,"[CR]")))*AA27} -> 120
A28: T15 | B28: Cash | C28: ='Personal (Basis)'!$C$28 -> 4695.6522 | F28: Total | H28: =SUBTOTAL(109,Personal_ETF[DR]) -> 47.540182 | I28: =SUBTOTAL(109,Personal_ETF[CR]) -> 47.540182 | K28: Total | M28: =SUBTOTAL(109,Personal_USD[DR]) -> 23908.696 | N28: =SUBTOTAL(109,Personal_USD[CR]) -> 23908.696 | P28: Total | R28: =SUBTOTAL(109,Personal_USDStock[DR]) -> 100 | S28: =SUBTOTAL(109,Personal_USDStock[CR]) -> 100 | U28: Total | W28: =SUBTOTAL(109,Personal_Oranges[DR]) -> 4608.6957 | X28: =SUBTOTAL(109,Personal_Oranges[CR]) -> 4608.6957 | AA28: 1 | AE28: Telecom Expense | AF28: {=SUMPRODUCT(--(INDIRECT(_xlfn.CONCAT($Z$2,"_",AB$1,"[Account]"))=AE28),INDIRECT(_xlfn.CONCAT($Z$2,"_",AB$1,"[DR]"))-INDIRECT(_xlfn.CONCAT($Z$2,"_",AB$1,"[CR]")))*AA28} -> 110
A29: T15 | B29: Net Transfers - Oranges | D29: ='Personal (Basis)'!$D$28 -> 2608.6957 | AA29: 1 | AE29: Transportation Expense | AF29: {=SUMPRODUCT(--(INDIRECT(_xlfn.CONCAT($Z$2,"_",AB$1,"[Account]"))=AE29),INDIRECT(_xlfn.CONCAT($Z$2,"_",AB$1,"[DR]"))-INDIRECT(_xlfn.CONCAT($Z$2,"_",AB$1,"[CR]")))*AA29} -> 200
A30: T15 | B30: Profit | D30: ='Personal (Basis)'!$I$28 -> 2086.9565 | AA30: 1 | AE30: GST Expense | AF30: {=SUMPRODUCT(--(INDIRECT(_xlfn.CONCAT($Z$2,"_",AB$1,"[Account]"))=AE30),INDIRECT(_xlfn.CONCAT($Z$2,"_",AB$1,"[DR]"))-INDIRECT(_xlfn.CONCAT($Z$2,"_",AB$1,"[CR]")))*AA30} -> 5
AE31: Less: Total Expenses | AG31: =-SUM(AF27:AF31) -> -435
AD32: Net Income | AH32: =SUM(AG18:AG31) -> -8953.4988
AC33: Net Worth | AI33: =SUM(AH13:AH32) -> 21046.501
AB34: Ledger Balance | AI34: =AI10-AI33 -> 0
A36: Total | C36: =SUBTOTAL(109,Personal_CAD[DR]) -> 66816.501 | D36: =SUBTOTAL(109,Personal_CAD[CR]) -> 66816.501

Sheet Personal (Basis)
B2: CAD - Cash | K2: ETF - Investment Portfolio | U2: USD - Cash & Receivables | AD2: USDStock - Investment Portfolio | AM2: Oranges - Inventory
B3: Lot A | K3: Lot A | M3: =M5/L5 -> 265 | U3: Lot A | AD3: Lot A | AH3: =AH5/AE5 -> 100 | AM3: Lot A | AO3: =AO5/AN5 -> 3.0666667 | AQ3: =AQ5/AN5 -> 2.3
B4: Trans. | C4: Delta | D4: CAD | E4: ETF | F4: USD | G4: USDStock | H4: Oranges | I4: Gain/Profit | K4: Trans. | L4: Delta | M4: CAD | N4: ETF | O4: USD | P4: USDStock | Q4: Oranges | R4: Gain/Profit | U4: Trans. | V4: Delta | W4: CAD | X4: ETF | Y4: USD | Z4: USDStock | AA4: Oranges | AB4: Gain/Profit | AD4: Trans. | AE4: Delta | AF4: CAD | AG4: ETF | AH4: USD | AI4: USDStock | AJ4: Oranges | AK4: Gain/Profit | AM4: Trans. | AN4: Delta | AO4: CAD | AP4: ETF | AQ4: USD | AR4: USDStock | AS4: Oranges | AT4: Gain/Profit
B5: IS | C5: =Personal!$C$4 -> 30000 | K5: T1 | L5: =M5/265 -> 37.735849 | M5: =-C6 -> 10000 | U5: IS | V5: 300 | AC5: =V6/(V6+V13) -> 0.06 | AD5: T9 | AE5: =Personal!$R$4*AC5 -> 3 | AH5: =-V6 -> 300 | AM5: T10 | AN5: =-V14/2.3 -> 1304.3478 | AO5: =-W14 -> 4000 | AQ5: =-V14 -> 3000
B6: T1 | C6: =-Personal!$D$7 -> -10000 | K6: T6 | L6: =-L5*25% -> -9.4339623 | M6: =M3*L6 -> -2500 | U6: T9 | V6: =-V5 -> -300 | AD6: T15 | AE6: =-AE5 -> -3 | AH6: =AH3*AE6 -> -300 | AM6: T11 | AN6: =-Personal!$X$7 -> -300 | AO6: =AO3*AN6 -> -920 | AQ6: =AQ3*AN6 -> -690
B7: T2 | C7: =-Personal!$D$9 -> -120 | AM7: T12 | AN7: =-Personal!$X$9 -> -700 | AO7: =AO3*AN7 -> -2146.6667 | AQ7: =AQ3*AN7 -> -1610
B8: T3 | C8: =-Personal!$D$12 -> -115 | K8: Total | L8: =SUM(L5:L7) -> 28.301887 | M8: =SUM(M5:M7) -> 7500 | N8: =SUM(N5:N7) -> 0 | O8: =SUM(O5:O7) -> 0 | P8: =SUM(P5:P7) -> 0 | Q8: =SUM(Q5:Q7) -> 0 | R8: =SUM(R5:R7) -> 0 | U8: Total | V8: =SUM(V5:V7) -> 0 | W8: =SUM(W5:W7) -> 0 | X8: =SUM(X5:X7) -> 0 | Y8: =SUM(Y5:Y7) -> 0 | Z8: =SUM(Z5:Z7) -> 0 | AA8: =SUM(AA5:AA7) -> 0 | AB8: =SUM(AB5:AB7) -> 0 | AD8: Total | AE8: =SUM(AE5:AE7) -> 0 | AF8: =SUM(AF5:AF7) -> 0 | AG8: =SUM(AG5:AG7) -> 0 | AH8: =SUM(AH5:AH7) -> 0 | AI8: =SUM(AI5:AI7) -> 0 | AJ8: =SUM(AJ5:AJ7) -> 0 | AK8: =SUM(AK5:AK7) -> 0 | AM8: T14 | AN8: =-SUM(AN5:AN7) -> -304.34783 | AO8: =AO3*AN8 -> -933.33333 | AQ8: =AQ3*AN8 -> -700
B9: T7 | C9: =-Personal!$D$22 -> -200
B10: T8 | C10: =-Personal!$D$24 -> -12000 | K10: Lot B | M10: =M12/L12 -> 270 | U10: Lot B | W10: =W12/V12 -> 1.3333333 | AM10: Total | AN10: =SUM(AN5:AN9) -> 0 | AO10: =SUM(AO5:AO9) -> 0 | AP10: =SUM(AP5:AP9) -> 0 | AQ10: =SUM(AQ5:AQ9) -> 0 | AR10: =SUM(AR5:AR9) -> 0 | AS10: =SUM(AS5:AS9) -> 0 | AT10: =SUM(AT5:AT9) -> 0
K11: Trans. | L11: Delta | M11: CAD | N11: ETF | O11: USD | P11: USDStock | Q11: Oranges | R11: Gain/Profit | U11: Trans. | V11: Delta | W11: CAD | X11: ETF | Y11: USD | Z11: USDStock | AA11: Oranges | AB11: Gain/Profit | AD11: Lot B | AF11: =AF13/AE13 -> 133.33333 | AH11: =AH13/AE13 -> 100
B12: Total | C12: =SUM(C5:C11) -> 7565 | D12: =SUM(D5:D11) -> 0 | E12: =SUM(E5:E11) -> 0 | F12: =SUM(F5:F11) -> 0 | G12: =SUM(G5:G11) -> 0 | H12: =SUM(H5:H11) -> 0 | I12: =SUM(I5:I11) -> 0 | K12: T5 | L12: =M12/270 -> 0.37037037 | M12: =Personal!$D$17 -> 100 | U12: T8 | V12: =-C10*0.75 -> 9000 | W12: =-C10 -> 12000 | AD12: Trans. | AE12: Delta | AF12: CAD | AG12: ETF | AH12: USD | AI12: USDStock | AJ12: Oranges | AK12: Gain/Profit | AM12: Lot B | AO12: =AO14/AN14 -> 3.3333333 | AQ12: =AQ14/AN14 -> 2.5
U13: T9 | V13: =-(Personal!$N$11+V6) -> -4700 | W13: =W10*V13 -> -6266.6667 | AC13: =V13/(V6+V13) -> 0.94 | AD13: T9 | AE13: =Personal!$R$4*AC13 -> 47 | AF13: =-W13 -> 6266.6667 | AH13: =-V13 -> 4700 | AM13: Trans. | AN13: Delta | AO13: CAD | AP13: ETF | AQ13: USD | AR13: USDStock | AS13: Oranges | AT13: Gain/Profit
B14: Lot B | U14: T10 | V14: =-Personal!$N$13 -> -3000 | W14: =W10*V14 -> -4000 | AD14: T15 | AE14: =-(Personal!$R$6+AE6) -> -47 | AF14: =AF11*AE14 -> -6266.6667 | AH14: =AH11*AE14 -> -4700 | AL14: =V15/(V15+V22) -> 0.52 | AM14: T13 | AN14: =-($V$15+$V$22)/2.5*AL14 -> 520 | AO14: =-W15 -> 1733.3333 | AQ14: =-V15 -> 1300
B15: Trans. | C15: Delta | D15: CAD | E15: ETF | F15: USD | G15: USDStock | H15: Oranges | I15: Gain/Profit | U15: T13 | V15: =-SUM(V12:V14) -> -1300 | W15: =W10*V15 -> -1733.3333 | AM15: T14 | AN15: =-(Personal!$W$12+AN8) -> -217.3913 | AO15: =AO12*AN15 -> -724.63768 | AQ15: =AQ12*AN15 -> -543.47826
B16: T4 | C16: =Personal!$C$13 -> 3000 | AD16: Total | AE16: =SUM(AE13:AE15) -> 0 | AF16: =SUM(AF13:AF15) -> 0 | AG16: =SUM(AG13:AG15) -> 0 | AH16: =SUM(AH13:AH15) -> 0 | AI16: =SUM(AI13:AI15) -> 0 | AJ16: =SUM(AJ13:AJ15) -> 0 | AK16: =SUM(AK13:AK15) -> 0 | AM16: T15 | AN16: =-SUM(AN14:AN15) -> -302.6087 | AO16: =AN16*AO12 -> -1008.6957 | AQ16: =AQ12*AN16 -> -756.52174
U17: Total | V17: =SUM(V12:V16) -> 0 | W17: =SUM(W12:W16) -> 0 | X17: =SUM(X12:X16) -> 0 | Y17: =SUM(Y12:Y16) -> 0 | Z17: =SUM(Z12:Z16) -> 0 | AA17: =SUM(AA12:AA16) -> 0 | AB17: =SUM(AB12:AB16) -> 0
B18: Lot C | AM18: Total | AN18: =SUM(AN14:AN17) -> 0 | AO18: =SUM(AO14:AO17) -> 0 | AP18: =SUM(AP14:AP17) -> 0 | AQ18: =SUM(AQ14:AQ17) -> 0 | AR18: =SUM(AR14:AR17) -> 0 | AS18: =SUM(AS14:AS17) -> 0 | AT18: =SUM(AT14:AT17) -> 0
B19: Trans. | C19: Delta | D19: CAD | E19: ETF | F19: USD | G19: USDStock | H19: Oranges | I19: Gain/Profit | U19: Lot C | W19: =W21/V21 -> 0.76666667 | Y19: =Y21/V21 -> 0.575
B20: T6 | C20: =-L6*290 -> 2735.8491 | D20: =-M6 -> 2500 | I20: =C20-D20 -> 235.84906 | U20: Trans. | V20: Delta | W20: CAD | X20: ETF | Y20: USD | Z20: USDStock | AA20: Oranges | AB20: Gain/Profit | AM20: Lot C | AO20: =AO22/AN22 -> 3.3333333 | AQ20: =AQ22/AN22 -> 2.5
U21: T11 | V21: =Personal!$M$14 -> 1200 | W21: =-AO6 -> 920 | Y21: =-AQ6 -> 690 | AB21: =V21-Y21 -> 510 | AM21: Trans. | AN21: Delta | AO21: CAD | AP21: ETF | AQ21: USD | AR21: USDStock | AS21: Oranges | AT21: Gain/Profit
B22: Lot D | D22: =D24/C24 -> 0.55757576 | F22: =F24/C24 -> 0.41818182 | U22: T13 | V22: =-(Personal!$N$18+V15) -> -1200 | W22: =W19*V22 -> -920 | Y22: =Y19*V22 -> -690 | AL22: =V22/(V15+V22) -> 0.48 | AM22: T13 | AN22: =-($V$15+$V$22)/2.5*AL22 -> 480 | AO22: =W21/Y21*AQ22 -> 1600 | AQ22: =-V22 -> 1200
B23: Trans. | C23: Delta | D23: CAD | E23: ETF | F23: USD | G23: USDStock | H23: Oranges | I23: Gain/Profit | AM23: T15 | AN23: =-(Personal!$X$15+AN16) -> -480 | AO23: =AO20*AN23 -> -1600 | AQ23: =AQ20*AN23 -> -1200
B24: T12 | C24: =Personal!$C$25 -> 3850 | D24: =-AO7 -> 2146.6667 | F24: =-AQ7 -> 1610 | I24: =C24-D24 -> 1703.3333 | U24: Total | V24: =SUM(V21:V23) -> 0 | W24: =SUM(W21:W23) -> 0 | X24: =SUM(X21:X23) -> 0 | Y24: =SUM(Y21:Y23) -> 0 | Z24: =SUM(Z21:Z23) -> 0 | AA24: =SUM(AA21:AA23) -> 0 | AB24: =SUM(AB21:AB23) -> 510
AM25: Total | AN25: =SUM(AN22:AN24) -> 0 | AO25: =SUM(AO22:AO24) -> 0 | AP25: =SUM(AP22:AP24) -> 0 | AQ25: =SUM(AQ22:AQ24) -> 0 | AR25: =SUM(AR22:AR24) -> 0 | AS25: =SUM(AS22:AS24) -> 0 | AT25: =SUM(AT22:AT24) -> 0
B26: Lot E | U26: Lot D
B27: Trans. | C27: Delta | D27: CAD | E27: ETF | F27: USD | G27: USDStock | H27: Oranges | I27: Gain/Profit | U27: Trans. | V27: Delta | W27: CAD | X27: ETF | Y27: USD | Z27: USDStock | AA27: Oranges | AB27: Gain/Profit
B28: T15 | C28: =-(AN23+AN16)*6 -> 4695.6522 | D28: =-(AO16+AO23) -> 2608.6957 | F28: =-(AQ16+AQ23) -> 1956.5217 | I28: =C28-D28 -> 2086.9565 | T28: =AN8/(AN8+AN15) -> 0.58333333 | U28: T14 | V28: =-(AN8+AN15)*5*T28 -> 1521.7391 | W28: =-AO16 -> 1008.6957 | Y28: =-AQ16 -> 756.52174 | AB28: =V28-Y28 -> 765.21739
U30: Lot E
U31: Trans. | V31: Delta | W31: CAD | X31: ETF | Y31: USD | Z31: USDStock | AA31: Oranges | AB31: Gain/Profit
T32: =AN15/(AN8+AN15) -> 0.41666667 | U32: T14 | V32: =-(AN8+AN15)*5*T32 -> 1086.9565 | W32: =-AO15 -> 724.63768 | Y32: =-AQ15 -> 543.47826 | AB32: =V32-Y32 -> 543.47826
U34: Lot F
U35: Trans. | V35: Delta | W35: CAD | X35: ETF | Y35: USD | Z35: USDStock | AA35: Oranges | AB35: Gain/Profit
T36: =AE6/(AE6+AE14) -> 0.06 | U36: T15
T38: =AE14/(AE6+AE14) -> 0.94 | U38: Lot G
U39: Trans. | V39: Delta | W39: CAD | X39: ETF | Y39: USD | Z39: USDStock | AA39: Oranges | AB39: Gain/Profit
U40: T15
